AUTHORS
LICENSE
MANIFEST.in
README.md
setup.py
Sharrock_Client.egg-info/PKG-INFO
Sharrock_Client.egg-info/SOURCES.txt
Sharrock_Client.egg-info/dependency_links.txt
Sharrock_Client.egg-info/requires.txt
Sharrock_Client.egg-info/top_level.txt
sharrock/__init__.py
sharrock/client.py