Metadata-Version: 1.0
Name: Sharrock-Client
Version: 0.6.3.3
Summary: Client for Sharrock Python RPC framework.
Home-page: https://github.com/Axilent/sharrock-client
Author: Loren Davie
Author-email: code@axilent.com
License: BSD
Platform: UNKNOWN
Classifier: Development Status :: 4 - Beta
Classifier: Environment :: Web Environment
Classifier: Intended Audience :: Developers
Classifier: License :: OSI Approved :: BSD License
Classifier: Programming Language :: Python
Classifier: Topic :: Software Development :: Libraries :: Python Modules
